<?xml version="1.0" encoding="utf-8"?>
<odoo>
    <data>
        <template id="sh_pos_receipt" name="sh_pos_theme_assets" inherit_id="point_of_sale.assets">
            <xpath expr="." position="inside">
            	<script type="text/javascript" src="/sh_pos_receipt/static/src/js/JsBarcode.all.min.js"/>
                <link rel="stylesheet" href="/sh_pos_receipt/static/src/css/pos_receipt.css"></link>
                <script type="text/javascript" src="/sh_pos_receipt/static/src/js/pos_receipt_invoice_number.js"></script>
            </xpath>
        </template>
    </data>
</odoo>