<?xml version="1.0" encoding="utf-8"?>
<odoo>
	<record id="res_partner_view_inherit_telenor_sms" model="ir.ui.view">
        <field name="name">res.partner.inherit.sms</field>
        <field name="model">res.partner</field>
        <field name="inherit_id" ref="base.view_partner_form"/>
        <field name="arch" type="xml">
            <xpath expr="//form/sheet" position="before">
                <header>
                    <button name="action_open_sms_wizard" type="object" string="Send SMS" class="oe_highlight"/>
                </header>
            </xpath>
        </field>
    </record>
</odoo>
